{"cameraMode":{"drawMode":0,"name":"Shaded","section":"Shading Mode"},"sceneLighting":true,"audioPlay":false,"sceneViewState":{"showFog":true,"showMaterialUpdate":false,"showSkybox":true,"showFlares":true,"showImageEffects":true,"showParticleSystems":true},"in2DMode":false,"pivot":{"x":8.13040542602539,"y":0.9117735624313355,"z":0.14722299575805665},"rotation":{"x":-0.14669327437877656,"y":-0.033528879284858707,"z":0.004975352436304092,"w":-0.9886018633842468},"size":1.8751767873764039,"orthographic":false}